[{"labelId":5,"name":{"ru":"Аниме","uk":"Аніме"},"color":"#e6a23c","ratingId":2,"visitorId":0,"dateCreate":"2023-05-19T00:31:40.000Z","dateUpdate":"2023-05-19T00:31:40.000Z"},{"labelId":4,"name":{"ru":"Без регистрации","uk":"Без реєстрації"},"color":"#67c23a","ratingId":2,"visitorId":0,"dateCreate":"2023-05-19T00:31:07.166Z","dateUpdate":"2023-05-19T00:31:07.166Z"},{"labelId":6,"name":{"ru":"Игры","uk":"Ігри"},"color":"#4780ad","ratingId":2,"visitorId":0,"dateCreate":"2023-05-19T00:32:37.662Z","dateUpdate":"2023-05-19T00:32:37.662Z"},{"labelId":7,"name":{"ru":"Программы","uk":"Програми"},"color":"#409eff","ratingId":2,"visitorId":0,"dateCreate":"2023-05-19T00:33:38.889Z","dateUpdate":"2023-05-19T00:34:16.356Z"},{"labelId":3,"name":{"ru":"Регистрация","uk":"Реєстрація"},"color":"#e94b3c","ratingId":2,"visitorId":0,"dateCreate":"2023-05-19T00:30:17.562Z","dateUpdate":"2023-05-19T00:30:17.562Z"}]
